philosim/__init__.py
philosim/main.py
philosim/prompts.py
philosim-2025.12.21095947.dist-info/METADATA
philosim-2025.12.21095947.dist-info/WHEEL
philosim-2025.12.21095947.dist-info/top_level.txt
philosim-2025.12.21095947.dist-info/RECORD
