Metadata-Version: 2.4
Name: philosim
Version: 2025.12.21095947
Summary: A new package that leverages the power of llmatch-messages to provide structured insights into complex philosophical and scientific topics, such as the simulation hypothesis. Users can input a specifi
Author-email: philosim <hi@eugene.plus>
License: MIT
Project-URL: Homepage, https://github.com/chigwell/philosim
Requires-Python: >=3.9
Requires-Dist: langchain-llm7>=0.0.0
Requires-Dist: llmatch-messages>=0.0.0
Requires-Dist: langchain-core>=0.3.0
